LICENSE
README.md
setup.py
BioPathAI.egg-info/PKG-INFO
BioPathAI.egg-info/SOURCES.txt
BioPathAI.egg-info/dependency_links.txt
BioPathAI.egg-info/entry_points.txt
BioPathAI.egg-info/not-zip-safe
BioPathAI.egg-info/requires.txt
BioPathAI.egg-info/top_level.txt
biopathai/__init__.py
biopathai/biopathai.py
biopathai/modules/__init__.py
biopathai/modules/evaluate.py
biopathai/modules/prepare.py
scripts/biopathai_pvalue.py