Metadata-Version: 2.1
Name: BioPathAI
Version: 0.1.0
Summary: BioPathAI: a Python tool for the analysis of biological pathways with machine learning techniques
Home-page: http://github.com/cumbof/BioPathAI
Author: Fabio Cumbo
Author-email: fabio.cumbo@gmail.com
License: MIT
Download-URL: https://pypi.org/project/BioPathAI/
Project-URL: Issues, https://github.com/cumbof/BioPathAI/issues
Project-URL: Source, https://github.com/cumbof/BioPathAI
Keywords: bioinformatics,machine learning,pathways
Platform: UNKNOWN
Classifier: Environment :: Console
Classifier: Intended Audience :: Science/Research
Classifier: License :: OSI Approved :: MIT License
Classifier: Natural Language :: English
Classifier: Operating System :: POSIX :: Linux
Classifier: Programming Language :: Python :: 3
Classifier: Topic :: Scientific/Engineering :: Bio-Informatics
Requires-Python: >=3.6
